signalytica/__init__.py
signalytica/signalytica.py
signalytica-0.1.20.dist-info/LICENSE
signalytica-0.1.20.dist-info/METADATA
signalytica-0.1.20.dist-info/WHEEL
signalytica-0.1.20.dist-info/top_level.txt
signalytica-0.1.20.dist-info/RECORD
