Metadata-Version: 2.1
Name: signalytica
Version: 0.1.20
Summary: Feature extraction for time series and EEG signals
Home-page: https://github.com/Edgar-La/signalytica
Author: Edgar Lara
Author-email: elara480@gmail.com
Classifier: Programming Language :: Python :: 3
Classifier: License :: OSI Approved :: MIT License
Classifier: Operating System :: OS Independent
Requires-Python: >=3.7
License-File: LICENSE
Requires-Dist: scipy (==1.7.3)
Requires-Dist: numpy (==1.21.6)
